conditioner/__init__.py
conditioner/admin.py
conditioner/apps.py
conditioner/base.py
conditioner/exceptions.py
conditioner/models.py
conditioner/utils.py
conditioner/actions/__init__.py
conditioner/actions/common.py
conditioner/actions/forms.py
conditioner/actions/misc.py
conditioner/conditions/__init__.py
conditioner/conditions/dates.py
conditioner/conditions/signals.py
conditioner/management/__init__.py
conditioner/management/commands/__init__.py
conditioner/management/commands/run_cron_conditions.py
conditioner/migrations/0001_initial.py
conditioner/migrations/__init__.py
conditioner/tests/__init__.py
conditioner/tests/factories.py
conditioner/tests/test_apps.py
conditioner/tests/test_base.py
conditioner/tests/test_models.py
conditioner/tests/test_utils.py
conditioner/tests/actions/__init__.py
conditioner/tests/actions/factories.py
conditioner/tests/actions/test_common.py
conditioner/tests/actions/test_forms.py
conditioner/tests/actions/test_misc.py
conditioner/tests/conditions/__init__.py
conditioner/tests/conditions/factories.py
conditioner/tests/conditions/test_dates.py
conditioner/tests/conditions/test_signals.py
django_conditioner-0.1.0.dist-info/DESCRIPTION.rst
django_conditioner-0.1.0.dist-info/METADATA
django_conditioner-0.1.0.dist-info/RECORD
django_conditioner-0.1.0.dist-info/WHEEL
django_conditioner-0.1.0.dist-info/metadata.json
django_conditioner-0.1.0.dist-info/top_level.txt
