Metadata-Version: 2.0
Name: django-conditioner
Version: 0.1.0
Summary: Create simple 'if this then that' style rules in your Django application. Comes with a bunch of ready to use actions and conditions, but is also easily extensible and allows model specific actions/conditions.
Home-page: https://github.com/omni-digital/django-conditioner
Author: Omni Digital
Author-email: dev@omni-digital.co.uk
License: MIT License
Download-URL: https://github.com/omni-digital/django-conditioner/releases/latest
Keywords: django conditions ifttt
Platform: UNKNOWN
Classifier: Development Status :: 4 - Beta
Classifier: Framework :: Django
Classifier: Framework :: Django :: 1.8
Classifier: Framework :: Django :: 1.9
Classifier: Framework :: Django :: 1.10
Classifier: Intended Audience :: Developers
Classifier: License :: OSI Approved :: MIT License
Classifier: Operating System :: OS Independent
Classifier: Programming Language :: Python
Classifier: Programming Language :: Python :: 3
Classifier: Programming Language :: Python :: 3.4
Classifier: Programming Language :: Python :: 3.5
Classifier: Programming Language :: Python :: 3.6
Classifier: Topic :: Software Development :: Libraries :: Python Modules
Requires-Dist: django-polymorphic (>=1.1)
